<?xml version="1.0" encoding="UTF-8"?>
<node lastupdate="02/09/2017 @ 03:18:20 PM">
  <node description="" type="IMG" label="wfAttract" name="WFattract" id="54563242">Objects/WayFinderIntroImage.png</node>
  <node description="" type="SWF" label="Gate%5Foff" name="gatesoff" id="4441">Objects/Gates_Off.swf</node>
  <node description="" type="SWF" label="Gate%5Fon%5F" name="gateson" id="4442">Objects/Gates_On.swf</node>
  <node description="" type="SWF" label="Toilets%20and%20Showers%5FOn" name="toiletsandShowerson" id="2093901114">Objects/ToiletsandShowers_On.swf</node>
  <node description="" type="SWF" label="Toilets%20and%20Showers%5FOff" name="toiletsandShowersoff" id="4212812952">Objects/ToiletsandShowers_Off.swf</node>
  <node description="" type="SWF" label="Food%20and%20Beverages%5Fon" name="foodandbeverageson" id="6772911242">Objects/FoodandBeverages_On.swf</node>
  <node description="" type="SWF" label="Food%20and%20Beverages%5FOff" name="foodandbeveragesoff" id="4473924253">Objects/FoodandBeverages_Off.swf</node>
  <node description="" type="SWF" label="Other%20Services%5FOff" name="otherservicesoff" id="1052812952">Objects/Otherservices_Off.swf</node>
  <node description="" type="SWF" label="Other%20Services%5FOn" name="otherserviceson" id="6423390111">Objects/Otherservices_On.swf</node>
  <node description="" type="SWF" label="Shopping%20Entertainment%5FOn" name="shoppingon" id="8919484853">Objects/Dutyfreeshopping_On.swf</node>
  <node description="" type="SWF" label="Shopping%20Entertainment%5FOff" name="shoppingoff" id="5762739884">Objects/Dutyfreeshopping_Off.swf</node>
  <node description="" type="SWF" label="Beauty%20Relaxation%5FOn" name="beautyon" id="4372901114">Objects/BeautyandRelaxation_On.swf</node>
  <node description="" type="SWF" label="Beauty%20Relaxation%5FOff" name="beautyoff" id="6732812952">Objects/BeautyandRelaxation_Off.swf</node>
  <node description="" type="SWF" label="Lounges%5Foff" name="loungesoff" id="490656519">Objects/Lounges_Off.swf</node>
  <node description="" type="SWF" label="Lounges%5Fon%5F" name="loungeson" id="3136563950">Objects/Lounges_On.swf</node>
  <node description="" type="SWF" label="Gate%5Foff%20AR" name="gatesoffar" id="14441">Objects/Gates_AR_Off.swf</node>
  <node description="" type="SWF" label="Gate%5Fon%20AR" name="gatesonar" id="14442">Objects/Gates_AR_On.swf</node>
  <node description="" type="SWF" label="Airport%5Foff%20AR" name="airportservicesoffar" id="24441">Objects/AirportServices_Ar_Off.swf</node>
  <node description="" type="SWF" label="Airport%5Fon%20AR" name="airportservicesonar" id="24442">Objects/AirportServices_Ar_On.swf</node>
  <node description="" type="SWF" label="Airport%5Foff" name="airportservicesoff" id="34441">Objects/AirportServices_Off.swf</node>
  <node description="" type="SWF" label="Airport%5Fon" name="airportserviceson" id="34442">Objects/AirportServices_On.swf</node>
  <node description="" type="SWF" label="Toilets%20and%20Showers%5FOn%20AR" name="toiletsandShowersonar" id="12093901114">Objects/ToiletsandShowers_AR_On.swf</node>
  <node description="" type="SWF" label="Toilets%20and%20Showers%5FOff%20AR" name="toiletsandShowersoffar" id="14212812952">Objects/ToiletsandShowers_AR_Off.swf</node>
  <node description="" type="SWF" label="Food%20and%20Beverages%5Fon%20AR" name="foodandbeveragesonar" id="16772911242">Objects/FoodandBeverages_AR_On.swf</node>
  <node description="" type="SWF" label="Food%20and%20Beverages%5FOff%20AR" name="foodandbeveragesoffar" id="14473924253">Objects/FoodandBeverages_AR_Off.swf</node>
  <node description="" type="SWF" label="Other%20Services%5FOff%20AR" name="otherservicesoffar" id="11052812952">Objects/Otherservices_AR_Off.swf</node>
  <node description="" type="SWF" label="Other%20Services%5FOn%20AR" name="otherservicesonar" id="16423390111">Objects/Otherservices_AR_On.swf</node>
  <node description="" type="SWF" label="Shopping%20Entertainment%5FOn%20AR" name="shoppingonar" id="18919484853">Objects/Dutyfreeshopping_AR_On.swf</node>
  <node description="" type="SWF" label="Shopping%20Entertainment%5FOff%20AR" name="shoppingoffar" id="15762739884">Objects/Dutyfreeshopping_AR_Off.swf</node>
  <node description="" type="SWF" label="Beauty%20Relaxation%5FOn%20AR" name="beautyonar" id="14372901114">Objects/BeautyandRelaxation_AR_On.swf</node>
  <node description="" type="SWF" label="Beauty%20Relaxation%5FOff%20AR" name="beautyoffar" id="16732812952">Objects/BeautyandRelaxation_AR_Off.swf</node>
  <node description="" type="SWF" label="Lounges%5Foff%20AR" name="loungesoffar" id="1490656519">Objects/Lounges_AR_Off.swf</node>
  <node description="" type="SWF" label="Lounges%5Fon%20AR" name="loungesonar" id="13136563950">Objects/Lounges_AR_On.swf</node>
  <node description="" type="SWF" label="Baggage%20Carousels%5FOff" name="baggageoff" id="3256901114">Objects/BaggageCarousels_Off.swf</node>
  <node description="" type="SWF" label="Baggage%20Carousels%5FOn" name="baggageon" id="8756812952">Objects/BaggageCarousels_On.swf</node>
  <node description="" type="SWF" label="TransportServices%5Foff" name="transportservicesoff" id="9812911242">Objects/TransportServices_Off.swf</node>
  <node description="" type="SWF" label="TransportServices%5FOn" name="transportserviceson" id="4523924253">Objects/TransportServices_On.swf</node>
  <node description="" type="SWF" label="Dutyfreeshopping%5FOff" name="dutyfreeshoppingoff" id="9034812952">Objects/Dutyfreeshopping_Off.swf</node>
  <node description="" type="SWF" label="Dutyfreeshopping%5FOn" name="dutyfreeshoppingon" id="5671390111">Objects/Dutyfreeshopping_On.swf</node>
  <node description="" type="SWF" label="FoodandBeverages%5FOff" name="foodandbeveragesoff" id="8730484853">Objects/FoodandBeverages_Off.swf</node>
  <node description="" type="SWF" label="FoodandBeverages%5FOn" name="foodandbeverageson" id="4316739884">Objects/FoodandBeverages_On.swf</node>
  <node description="" type="SWF" label="EntertainmentRelaxation%5FOff" name="entertainmentrelaxationoff" id="3219901114">Objects/EntertainmentRelaxation_Off.swf</node>
  <node description="" type="SWF" label="EntertainmentRelaxation%5FOn" name="entertainmentrelaxationon" id="6790812952">Objects/EntertainmentRelaxation_On.swf</node>
  <node description="" type="SWF" label="ToiletsandShowers%5Foff" name="toiletsandshowersoff" id="129056519">Objects/ToiletsandShowers_Off.swf</node>
  <node description="" type="SWF" label="ToiletsandShowers%5Fon%5F" name="toiletsandshowerson" id="3267563950">Objects/ToiletsandShowers_On.swf</node>
  <node description="" type="SWF" label="Otherservices%5Foff" name="otherservicesoff" id="23459801">Objects/Otherservices_Off.swf</node>
  <node description="" type="SWF" label="Otherservices%5Fon%5F" name="otherserviceson" id="23459802">Objects/Otherservices_On.swf</node>
  <node description="" type="SWF" label="Baggage%20Carousels%5FOff%20AR" name="baggageoffar" id="13256901114">Objects/BaggageCarousels_AR_Off.swf</node>
  <node description="" type="SWF" label="Baggage%20Carousels%5FOn" name="baggageonar" id="18756812952">Objects/BaggageCarousels_AR_On.swf</node>
  <node description="" type="SWF" label="TransportServices%5Foff%20AR" name="transportservicesoffar" id="19812911242">Objects/TransportServices_AR_Off.swf</node>
  <node description="" type="SWF" label="TransportServices%5FOn%20AR" name="transportservicesonar" id="14523924253">Objects/TransportServices_AR_On.swf</node>
  <node description="" type="SWF" label="Dutyfreeshopping%5FOff%20AR" name="dutyfreeshoppingoffar" id="19034812952">Objects/Dutyfreeshopping_AR_Off.swf</node>
  <node description="" type="SWF" label="Dutyfreeshopping%5FOn%20AR" name="dutyfreeshoppingonar" id="15671390111">Objects/Dutyfreeshopping_AR_On.swf</node>
  <node description="" type="SWF" label="FoodandBeverages%5FOff%20AR" name="foodandbeveragesoffar" id="18730484853">Objects/FoodandBeverages_AR_Off.swf</node>
  <node description="" type="SWF" label="FoodandBeverages%5FOn%20AR" name="foodandbeveragesonar" id="14316739884">Objects/FoodandBeverages_AR_On.swf</node>
  <node description="" type="SWF" label="EntertainmentRelaxation%5FOff%20AR" name="entertainmentrelaxationoffar" id="13219901114">Objects/EntertainmentRelaxation_AR_Off.swf</node>
  <node description="" type="SWF" label="EntertainmentRelaxation%5FOn%20AR" name="entertainmentrelaxationonar" id="16790812952">Objects/EntertainmentRelaxation_AR_On.swf</node>
  <node description="" type="SWF" label="ToiletsandShowers%5Foff%20AR" name="toiletsandshowersoffar" id="1129056519">Objects/ToiletsandShowers_AR_Off.swf</node>
  <node description="" type="SWF" label="ToiletsandShowers%5Fon%5F%20AR" name="toiletsandshowersonar" id="13267563950">Objects/ToiletsandShowers_AR_On.swf</node>
  <node description="" type="SWF" label="Otherservices%5Foff%20AR" name="otherservicesoffar" id="123459801">Objects/Otherservices_AR_Off.swf</node>
  <node description="" type="SWF" label="Otherservices%5Fon%5F%20AR" name="otherservicesonar" id="123459802">Objects/Otherservices_AR_On.swf</node>
  <node description="" type="SWF" label="CheckIn%20Counters%5FOff" name="countersoff" id="67236901114">Objects/CheckIn_Off.swf</node>
  <node description="" type="SWF" label="CheckIn%20Counters%5FOn" name="counterson" id="65780812952">Objects/CheckIn_On.swf</node>
  <node description="" type="SWF" label="Gates%5Foff" name="gatesoff" id="3671911242">Objects/101-160_Gates_Off.swf</node>
  <node description="" type="SWF" label="Gates%5FOn" name="gateson" id="67363924253">Objects/101-160_Gates_On.swf</node>
  <node description="" type="SWF" label="CheckIn%20Counters%5FOff" name="countersaroff" id="34126901114">Objects/CheckIn_Ar_Off.swf</node>
  <node description="" type="SWF" label="CheckIn%20Counters%5FOn" name="countersaron" id="98030812952">Objects/CheckIn_Ar_On.swf</node>
  <node description="" type="SWF" label="Gates%5Foff" name="gatesaroff" id="4267911242">Objects/101-160_Gates_Ar_Off.swf</node>
  <node description="" type="SWF" label="Gates%5FOn" name="gatesaron" id="76903924253">Objects/101-160_Gates_Ar_On.swf</node>
  <node description="" type="SWF" label="101%2D260%5FGates%5FOff" name="gatesoff" id="4671911242">Objects/101-260_Gates_Off.swf</node>
  <node description="" type="SWF" label="101%2D260%5FGates%5FOn" name="gateson" id="47363924253">Objects/101-260_Gates_On.swf</node>
  <node description="" type="SWF" label="101%2D260%5FGates%5FAr%5FOff" name="gatesaroff" id="5267911242">Objects/101-260_Gates_Ar_Off.swf</node>
  <node description="" type="SWF" label="101%2D260%5FGates%5FAr%5FOn" name="gatesaron" id="56903924253">Objects/101-260_Gates_Ar_On.swf</node>
  <node description="" type="SWF" label="Prayer%5Froom%5FOff" name="prayeroff" id="84758911242">Objects/PrayerRooms_Off.swf</node>
  <node description="" type="SWF" label="Prayer%5Froom%5FOn" name="prayeron" id="5238756442">Objects/PrayerRooms_On.swf</node>
  <node description="" type="SWF" label="Prayer%5Froom%5FOff" name="prayeraroff" id="537889134267">Objects/PrayerRooms_Ar_Off.swf</node>
  <node description="" type="SWF" label="Prayer%5Froom%5FOn" name="prayeraron" id="537889131907">Objects/PrayerRooms_Ar_On.swf</node>
  <node id="9441" name="baggagearrivaloff" label="Baggage%5Foff" type="SWF"	description="">Objects/Baggage_Claim_off.swf</node>
  <node id="9442" name="baggagearrivalon" label="Baggage%5Fon" type="SWF" description="">Objects/Baggage_Claim_on.swf</node>
  <node id="123456" name="shangrilaimage1" label="Shangri%2DLa%20Image%201" type="IMG" description="Shangri%2DLa%20Image%201">Objects/ShangriLaImage.jpg</node>
  <node id="123457" name="shangrilaimage2" label="Shangri%2DLa%20Image%202" type="IMG" description="Shangri%2DLa%20Image%202">Objects/ShangriLaImage2.jpg</node>
  <node id="123458" name="shangrilamap1" label="Shangri%2DLa%20Map%201" type="IMG" description="Shangri%2DLa%20Map%201">Objects/ShangriLaMap.jpg</node>
  <node id="123459" name="shangrilamap2" label="Shangri%2DLa%20Map%202" type="IMG" description="Shangri%2DLa%20Map%202">Objects/ShangriLaMap2.jpg</node>
  <node id="317" name="shangrilathumbnailmap1" label="Shangri%2DLa%20Thumbnail%201" type="IMG" description="Shangri%2DLa%20Thumbnail%201">Objects/Thumbnail_1_ShangriLaImage.jpg</node>
  <node id="320" name="shangrilathumbnailmap2" label="Shangri%2DLa%20Thumbnail%202" type="IMG" description="Shangri%2DLa%20Thumbnail%202">Objects/Thumbnail_2_ShangriLaImage.jpg</node>
  <node id="3109090909" name="shangrilathumbnailmap3" label="Shangri%2DLa%20Thumbnail%203" type="IMG" description="Shangri%2DLa%20Thumbnail%203">Objects/Thumbnail_3_ShangriLaImage.jpg</node>
  <node id="3109090910" name="shangrilathumbnailmap4" label="Shangri%2DLa%20Thumbnail%204" type="IMG" description="Shangri%2DLa%20Thumbnail%204">Objects/Thumbnail_4_ShangriLaImage.jpg</node>
  <node id="3109090911" name="shangrilathumbnailmap5" label="Shangri%2DLa%20Thumbnail%205" type="IMG" description="Shangri%2DLa%20Thumbnail%205">Objects/Thumbnail_5_ShangriLaImage.jpg</node>
  <node id="3109090912" name="shangrilathumbnailmap6" label="Shangri%2DLa%20Thumbnail%206" type="IMG" description="Shangri%2DLa%20Thumbnail%206">Objects/Thumbnail_6_ShangriLaImage.jpg</node>
  <node id="47993405841" name="MUSCATGOVERNORATE_T" label="MUSCAT%20GOVERNORATE" type="IMG" description="MUSCAT%20GOVERNORATE%20THUMB">Objects/4799340584_t.jpg</node>
  <node id="47993405842" name="MUSCATGOVERNORATE_L" label="MUSCAT%20GOVERNORATE" type="IMG" description="MUSCAT%20GOVERNORATE%20LARGE">Objects/4799340584_n.jpg</node>
  <node id="48148472761" name="DOFARGOVERNORATE_T" label="DOFAR%20GOVERNORATE" type="IMG" description="DOFAR%20GOVERNORATE%20THUMB">Objects/4814847276_t.jpg</node>
  <node id="48148472762" name="DOFARGOVERNORATE_L" label="DOFAR%20GOVERNORATE" type="IMG" description="DOFAR%20GOVERNORATE%20LARGE">Objects/4814847276_n.jpg</node>
  <node id="60612892491" name="MUSANDAMGOVERNORATE_T" label="MUSANDAM%20GOVERNORATE" type="IMG" description="MUSANDAM%20GOVERNORATE%20THUMB">Objects/6061289249_t.jpg</node>
  <node id="60612892492" name="MUSANDAMGOVERNORATE_L" label="MUSANDAM%20GOVERNORATE" type="IMG" description="MUSANDAM%20GOVERNORATE%20LARGE">Objects/6061289249_n.jpg</node>
  <node id="51021540621" name="ALBATINAHREGION_T" label="ALBATINAH%20GOVERNORATE" type="IMG" description="AL%20BATINAH%20REGION%20THUMB">Objects/5102154062_t.jpg</node>
  <node id="51021540622" name="ALBATINAHREGION_L" label="ALBATINAH%20GOVERNORATE" type="IMG" description="AL%20BATINAH%20REGION%20LARGE">Objects/5102154062_n.jpg</node>
  <node id="48121695161" name="ADDAKHILIYAHREGION_T" label="ADDAKHILIYAH%20GOVERNORATE" type="IMG" description="ADDAKHILIYAH%20REGION%20THUMB">Objects/4812169516_t.jpg</node>
  <node id="48121695162" name="ADDAKHILIYAHREGION_L" label="ADDAKHILIYAH%20GOVERNORATE" type="IMG" description="ADDAKHILIYAH%20REGION%20LARGE">Objects/4812169516_n.jpg</node>
  <node id="48147859561" name="ASHSHARQIYAHREGION_T" label="ASHSHARQIYAH%20GOVERNORATE" type="IMG" description="ASHSHARQIYAH%20REGION%20THUMB">Objects/4814785956_t.jpg</node>
  <node id="48147859562" name="ASHSHARQIYAHREGION_L" label="ASHSHARQIYAH%20GOVERNORATE" type="IMG" description="ASHSHARQIYAH%20REGION%20LARGE">Objects/4814785956_n.jpg</node>
  <node id="48147859561" name="ALBURAIMIGOVERNORATE_T" label="ALBURAIMI%20GOVERNORATE" type="IMG" description="ALBURAIMI%20GOVERNORATE%20THUMB">Objects/4814785956_t.jpg</node>
  <node id="48147859562" name="ALBURAIMIGOVERNORATE_L" label="ALBURAIMI%20GOVERNORATE" type="IMG" description="ALBURAIMI%20GOVERNORATE%20LARGE">Objects/4814785956_n.jpg</node>
  <node id="48140862351" name="ADDHAHIRAHGOVERNORATE_T" label="ADDHAHIRAH%20GOVERNORATE" type="IMG" description="ADDHAHIRAH%20REGION%20THUMB">Objects/4814086235_t.jpg</node>
  <node id="48140862352" name="ADDHAHIRAHGOVERNORATE_L" label="ADDHAHIRAH%20GOVERNORATE" type="IMG" description="ADDHAHIRAH%20REGION%20LARGE">Objects/4814086235_n.jpg</node>
  <node id="96151360241" name="ALWUSTAGOVERNORATE_T" label="ALWUSTA%20GOVERNORATE" type="IMG" description="ALWUSTA%20REGION%20THUMB">Objects/9615136024_t.jpg</node>
  <node id="96151360242" name="ALWUSTAGOVERNORATE_L" label="ALWUSTA%20GOVERNORATE" type="IMG" description="ALWUSTA%20REGION%20LARGE">Objects/9615136024_n.jpg</node>
  <node id="78105382961" name="MUTTRAHCORNICHE_T" label="MUTTRAH%20CORNICHE" type="IMG" description="MUTTRAH%20CORNICHE%20THUMB">Objects/7810538296_t.jpg</node>
  <node id="78105382962" name="MUTTRAHCORNICHE_L" label="MUTTRAH%20CORNICHE" type="IMG" description="MUTTRAH%20CORNICHE%20LARGE">Objects/7810538296_n.jpg</node>
  <node id="150808584761" name="ALBUSTAN_T" label="AL%20BUSTAN" type="IMG" description="AL%20BUSTAN%20BEACH%20THUMB">Objects/15080858476_t.jpg</node>
  <node id="150808584762" name="ALBUSTAN_L" label="AL%20BUSTAN" type="IMG" description="AL%20BUSTAN%20BEACH%20LARGE">Objects/15080858476_n.jpg</node>
  <node id="58230667991" name="ALUZAIBAH_T" label="AL%20UZAIBAH" type="IMG" description="AL%20UZAIBAH%20BEACH%20THUMB">Objects/5823066799_t.jpg</node>
  <node id="58230667992" name="ALUZAIBAH_L" label="AL%20UZAIBAH" type="IMG" description="AL%20UZAIBAH%20BEACH%20LARGE">Objects/5823066799_n.jpg</node>
  <node id="160333024321" name="ALQURUM_T" label="AL%20QURUM" type="IMG" description="AL%20QURUM%20BEACH%20THUMB">Objects/16033302432_t.jpg</node>
  <node id="160333024322" name="ALQURUM_L" label="AL%20QURUM" type="IMG" description="AL%20QURUM%20BEACH%20LARGE">Objects/16033302432_n.jpg</node>
  <node id="84542643101" name="DOFARBEACH_T" label="DOFAR%20BEACH" type="IMG" description="DOFAR%20BEACH%20THUMB">Objects/8454264310_t.jpg</node>
  <node id="84542643102" name="DOFARBEACH_L" label="DOFAR%20BEACH" type="IMG" description="DOFAR%20BEACH%20LARGE">Objects/8454264310_n.jpg</node>
  <node id="168777251121" name="SOHARCORNICHE_T" label="SOHAR%20CORNICHE" type="IMG" description="SOHAR%20CORNICHE%20THUMB">Objects/16877725112_t.jpg</node>
  <node id="168777251122" name="SOHARCORNICHE_L" label="SOHAR%20CORNICHE" type="IMG" description="SOHAR%20CORNICHE%20LARGE">Objects/16877725112_n.jpg</node>
  <node id="92070768291" name="ASSAWADIBEACH_T" label="AS%20SAWADI%20BEACH" type="IMG" description="AS%20SAWADI%20BEACH%20THUMB">Objects/9207076829_t.jpg</node>
  <node id="92070768292" name="ASSAWADIBEACH_L" label="AS%20SAWADI%20BEACH" type="IMG" description="AS%20SAWADI%20BEACH%20LARGE">Objects/9207076829_n.jpg</node>
  <node id="68711970841" name="RASALHADDBEACH_T" label="RAS%20AL%20HADD%20BEACH" type="IMG" description="RAS%20AL%20HADD%20BEACH%20THUMB">Objects/6871197084_t.jpg</node>
  <node id="68711970842" name="RASALHADDBEACH_L" label="RAS%20AL%20HADD%20BEACH" type="IMG" description="RAS%20AL%20HADD%20BEACH%20LARGE">Objects/6871197084_n.jpg</node>
  <node id="152759439321" name="ALWUSTABEACH_T" label="AL%20WUSTA%20BEACH" type="IMG" description="AL%20WUSTA%20BEACH%20THUMB">Objects/15275943932_t.jpg</node>
  <node id="152759439322" name="ALWUSTABEACH_L" label="AL%20WUSTA%20BEACH" type="IMG" description="AL%20WUSTA%20BEACH%20LARGE">Objects/15275943932_n.jpg</node>
  <node id="227459880841" name="DUQMBEACH_T" label="DUQM%20BEACH" type="IMG" description="DUQM%20BEACH%20THUMB">Objects/22745988084_t.jpg</node>
  <node id="227459880842" name="DUQMBEACH_L" label="DUQM%20BEACH" type="IMG" description="DUQM%20BEACH%20LARGE">Objects/22745988084_n.jpg</node>
  <node id="68621601151" name="ALHILLANIYAT_T" label="ALHILLANIYAT" type="IMG" description="ALHILLANIYAT%20THUMB">Objects/6862160115_t.jpg</node>
  <node id="68621601152" name="ALHILLANIYAT_L" label="ALHILLANIYAT" type="IMG" description="ALHILLANIYAT%20LARGE">Objects/6862160115_n.jpg</node>
  <node id="61586910651" name="DIMANIYATISLAND_T" label="DIMANIYAT%20ISLAND" type="IMG" description="DIMANIYAT%20ISLAND%20THUMB">Objects/6158691065_t.jpg</node>
  <node id="61586910652" name="DIMANIYATISLAND_L" label="DIMANIYAT%20ISLAND" type="IMG" description="DIMANIYAT%20ISLAND%20LARGE">Objects/6158691065_n.jpg</node>
  <node id="49137211421" name="MASIRAHISLAND_T" label="MASIRAH%20ISLAND" type="IMG" description="MASIRAH%20ISLAND%20THUMB">Objects/4913721142_t.jpg</node>
  <node id="49137211422" name="MASIRAHISLAND_L" label="MASIRAH%20ISLAND" type="IMG" description="MASIRAH%20ISLAND%20LARGE">Objects/4913721142_n.jpg</node>
  <node id="52974425281" name="BARRALHIKMANISLAND_T" label="BARR%20AL%20HIKMAN%20ISLAND" type="IMG" description="BARR%20AL%20HIKMAN%20ISLAND%20THUMB">Objects/5297442528_t.jpg</node>
  <node id="52974425282" name="BARRALHIKMANISLAND_L" label="BARR%20AL%20HIKMAN%20ISLAND" type="IMG" description="BARR%20AL%20HIKMAN%20ISLAND%20LARGE">Objects/5297442528_n.jpg</node>
  <node id="154302696241" name="HAWIYATNAJMPARK_T" label="HAWIYAT%20NAJM%20PARK%20ISLAND" type="IMG" description="HAWIYAT%20NAJM%20PARK%20THUMB">Objects/15430269624_t.jpg</node>
  <node id="154302696242" name="HAWIYATNAJMPARK_L" label="HAWIYAT%20NAJM%20PARK%20ISLAND" type="IMG" description="HAWIYAT%20NAJM%20PARK%20LARGE">Objects/15430269624_n.jpg</node>
  <node id="96687177211" name="WADIALKHOUD_T" label="WADI%20AL%20KHOUD" type="IMG" description="WADI%20AL%20KHOUD%20THUMB">Objects/9668717721_t.jpg</node>
  <node id="96687177212" name="WADIALKHOUD_L" label="WADI%20AL%20KHOUD" type="IMG" description="WADI%20AL%20KHOUD%20LARGE">Objects/9668717721_n.jpg</node>
  <node id="167260366651" name="WADIALARBIYEEN_T" label="WADI%20AL%20ARBIYEEN" type="IMG" description="WADI%20AL%20ARBIYEEN%20THUMB">Objects/16726036665_t.jpg</node>
  <node id="167260366652" name="WADIALARBIYEEN_L" label="WADI%20AL%20ARBIYEEN" type="IMG" description="WADI%20AL%20ARBIYEEN%20LARGE">Objects/16726036665_n.jpg</node>
  <node id="139853374871" name="WADIALDAYQAH_T" label="WADI%20AL%20DAYQAH" type="IMG" description="WADI%20AL%20DAYQAH%20THUMB">Objects/13985337487_t.jpg</node>
  <node id="139853374872" name="WADIALDAYQAH_L" label="WADI%20AL%20DAYQAH" type="IMG" description="WADI%20AL%20DAYQAH%20LARGE">Objects/13985337487_n.jpg</node>
  <node id="20899917121" name="WADIDARBAT_T" label="WADI%20DARBAT" type="IMG" description="WADI%20DARBAT%20THUMB">Objects/2089991712_t.jpg</node>
  <node id="20899917122" name="WADIDARBAT_L" label="WADI%20DARBAT" type="IMG" description="WADI%20DARBAT%20LARGE">Objects/2089991712_n.jpg</node>
  <node id="48533958391" name="WADIALABYAD_T" label="WADI%20AL%20ABYAD" type="IMG" description="WADI%20AL%20ABYAD%20THUMB">Objects/4853395839_t.jpg</node>
  <node id="48533958392" name="WADIALABYAD_L" label="WADI%20AL%20ABYAD" type="IMG" description="WADI%20AL%20ABYAD%20%20LARGE">Objects/4853395839_n.jpg</node>
  <node id="67809983751" name="WADIBANIAWF_T" label="WADI%20BANI%20AWF" type="IMG" description="WADI%20BANI%20AWF%20THUMB">Objects/6780998375_t.jpg</node>
  <node id="67809983752" name="WADIBANIAWF_L" label="WADI%20BANI%20AWF" type="IMG" description="WADI%20BANI%20AWF%20LARGE">Objects/6780998375_n.jpg</node>
  <node id="35665294521" name="WADIBANIKHAROUS_T" label="WADI%20BANI%20KHAROUS" type="IMG" description="WADI%20BANI%20KHAROUS%20THUMB">Objects/3566529452_t.jpg</node>
  <node id="35665294522" name="WADIBANIKHAROUS_L" label="WADI%20BANI%20KHAROUS" type="IMG" description="WADI%20BANI%20KHAROUS%20LARGE">Objects/3566529452_n.jpg</node>
  <node id="83403806671" name="WADIDAMM_T" label="WADI%20DAMM" type="IMG" description="WADI%20DAMM%20THUMB">Objects/8340380667_t.jpg</node>
  <node id="83403806672" name="WADIDAMM_L" label="WADI%20DAMM" type="IMG" description="WADI%20DAMM%20LARGE">Objects/8340380667_n.jpg</node>
  <node id="91046805721" name="WADIDANAKFIDA_T" label="WADI%20DANAK%20FIDA" type="IMG" description="WADI%20DANAK%20FIDA%20THUMB">Objects/9104680572_t.jpg</node>
  <node id="91046805722" name="WADIDANAKFIDA_L" label="WADI%20DANAK%20FIDA" type="IMG" description="WADI%20DANAK%20FIDA%20LARGE">Objects/9104680572_n.jpg</node>
  <node id="44126978271" name="WADIMUAYDEN_T" label="WADI%20MUAYDEN" type="IMG" description="WADI%20MUAYDEN%20THUMB">Objects/4412697827_t.jpg</node>
  <node id="44126978272" name="WADIMUAYDEN_L" label="WADI%20MUAYDEN" type="IMG" description="WADI%20MUAYDEN%20LARGE">Objects/4412697827_n.jpg</node>
  <node id="116405542351" name="WADIARRAWDHA_T" label="WADI%20ARRAWDHA" type="IMG" description="WADI%20ARRAWDHA%20THUMB">Objects/11640554235_t.jpg</node>
  <node id="116405542352" name="WADIARRAWDHA_L" label="WADI%20ARRAWDHA" type="IMG" description="WADI%20ARRAWDHA%20LARGE">Objects/11640554235_n.jpg</node>
  <node id="3626499771" name="WADIALSHAB_T" label="WADI%20AL%20SHAB" type="IMG" description="WADI%20AL%20SHAB%20THUMB">Objects/362649977_t.jpg</node>
  <node id="3626499772" name="WADIALSHAB_L" label="WADI%20AL%20SHAB" type="IMG" description="WADI%20AL%20SHAB%20LARGE">Objects/362649977_n.jpg</node>
  <node id="229092600991" name="WADITIWI_T" label="WADI%20TIWI" type="IMG" description="WADI%20TIWI%20THUMB">Objects/22909260099_t.jpg</node>
  <node id="229092600992" name="WADITIWI_L" label="WADI%20TIWI" type="IMG" description="WADI%20TIWI%20LARGE">Objects/22909260099_n.jpg</node>
  <node id="33036043621" name="WADIAL-TAAEEN_T" label="WADI%20AL%2DTAAEEN" type="IMG" description="WADI%20AL%2DTAAEEN%20THUMB">Objects/3303604362_t.jpg</node>
  <node id="33036043622" name="WADIAL-TAAEEN_L" label="WADI%20AL%2DTAAEEN" type="IMG" description="WADI%20AL%2DTAAEEN%20LARGE">Objects/3303604362_n.jpg</node>
  <node id="205547787391" name="WADIDIMMA_T" label="WADI%20DIMMA" type="IMG" description="WADI%20DIMMA%20THUMB">Objects/20554778739_t.jpg</node>
  <node id="205547787392" name="WADIDIMMA_L" label="WADI%20DIMMA" type="IMG" description="WADI%20DIMMA%20LARGE">Objects/20554778739_n.jpg</node>
  <node id="87072933211" name="WADIANDAM_T" label="WADI%20ANDAM" type="IMG" description="WADI%20ANDAM%20THUMB">Objects/8707293321_t.jpg</node>
  <node id="87072933212" name="WADIANDAM_L" label="WADI%20ANDAM" type="IMG" description="WADI%20ANDAM%20LARGE">Objects/8707293321_n.jpg</node>
  <node id="135532325841" name="WADIALHAWQAYN_T" label="WADI%20AL%20HAWQAYN" type="IMG" description="WADI%20AL%20HAWQAYN%20THUMB">Objects/13553232584_t.jpg</node>
  <node id="135532325842" name="WADIALHAWQAYN_L" label="WADI%20AL%20HAWQAYN" type="IMG" description="WADI%20AL%20HAWQAYN%20LARGE">Objects/13553232584_n.jpg</node>
  <node id="81529321611" name="TURTLERESERVE_T" label="TURTLE%20RESERVE" type="IMG" description="TURTLE%20RESERVE%20THUMB">Objects/8152932161_t.jpg</node>
  <node id="81529321612" name="TURTLERESERVE_L" label="TURTLE%20RESERVE" type="IMG" description="TURTLE%20RESERVE%20LARGE">Objects/8152932161_n.jpg</node>
  <node id="242599545161" name="ASSALEELNATUREPARK_T" label="AS%20SALEEL%20NATURE%20PARK" type="IMG" description="AS%20SALEEL%20NATURE%20PARK%20THUMB">Objects/24259954516_t.jpg</node>
  <node id="242599545162" name="ASSALEELNATUREPARK_L" label="AS%20SALEEL%20NATURE%20PARK" type="IMG" description="AS%20SALEEL%20NATURE%20PARK%20LARGE">Objects/24259954516_n.jpg</node>
  <node id="54303325241" name="ARABIANORYXSANCTUARY_T" label="ARABIAN%20ORYX%20SANCTUARY" type="IMG" description="ARABIAN%20ORYX%20SANCTUARY%20THUMB">Objects/5430332524_t.jpg</node>
  <node id="54303325242" name="ARABIANORYXSANCTUARY_L" label="ARABIAN%20ORYX%20SANCTUARY" type="IMG" description="ARABIAN%20ORYX%20SANCTUARY%20LARGE">Objects/5430332524_n.jpg</node>
  <node id="54599703371" name="TEEQCAVEANDTAWIATEERSINKHOLE_T" label="TEEQ%20CAVE%20AND%20TAWI%20ATEER%20SINKHOLE" type="IMG" description="TEEQ%20CAVE%20AND%20TAWI%20ATEER%20SINKHOLE%20THUMB">Objects/5459970337_t.jpg</node>
  <node id="54599703372" name="TEEQCAVEANDTAWIATEERSINKHOLE_L" label="TEEQ%20CAVE%20AND%20TAWI%20ATEER%20SINKHOLE" type="IMG" description="TEEQ%20CAVE%20AND%20TAWI%20ATEER%20SINKHOLE%20LARGE">Objects/5459970337_n.jpg</node>
  <node id="28514764061" name="ALKITTANCAVE_T" label="AL%20KITTAN%20CAVE" type="IMG" description="AL%20KITTAN%20CAVE%20THUMB">Objects/2851476406_t.jpg</node>
  <node id="28514764062" name="ALKITTANCAVE_L" label="AL%20KITTAN%20CAVE" type="IMG" description="AL%20KITTAN%20CAVE%20LARGE">Objects/2851476406_n.jpg</node>
  <node id="48140980571" name="ALHOOTACAVE_T" label="ALHOOTA%20CAVE" type="IMG" description="ALHOOTA%20CAVE%20THUMB">Objects/4814098057_t.jpg</node>
  <node id="48140980572" name="ALHOOTACAVE_L" label="ALHOOTA%20CAVE" type="IMG" description="ALHOOTA%20CAVE%20LARGE">Objects/4814098057_n.jpg</node>
  <node id="56598677431" name="ALHOOTACAVELAKE_T" label="ALHOOTA%20CAVE%20LAKE" type="IMG" description="ALHOOTA%20CAVE%20LAKE%20THUMB">Objects/5659867743_t.jpg</node>
  <node id="56598677432" name="ALHOOTACAVELAKE_L" label="ALHOOTA%20CAVE%20LAKE" type="IMG" description="ALHOOTA%20CAVE%20LAKE%20LARGE">Objects/5659867743_n.jpg</node>
  <node id="56599380431" name="MAJLISALJINNCAVE_T" label="MAJLIS%20AL%20JINN%20CAVE" type="IMG" description="MAJLIS%20AL%20JINN%20CAVE%20THUMB">Objects/5659938043_t.jpg</node>
  <node id="56599380432" name="MAJLISALJINNCAVE_L" label="MAJLIS%20AL%20JINN%20CAVE" type="IMG" description="MAJLIS%20AL%20JINN%20CAVE%20LARGE">Objects/5659938043_n.jpg</node>
  <node id="54599745411" name="MUQALCAVE _T" label="MUQAL%20CAVE" type="IMG" description="MUQAL%20CAVE%20THUMB">Objects/5459974541_t.jpg</node>
  <node id="54599745412" name="MUQALCAVE_L" label="MUQAL%20CAVE" type="IMG" description="MUQAL%20CAVE%20LARGE">Objects/5459974541_n.jpg</node>
  <node id="60452145161" name="BANDARKHAYRANRESERVE_T" label="BANDAR%20KHAYRAN%20RESERVE" type="IMG" description="BANDAR%20KHAYRAN%20RESERVE%20THUMB">Objects/6045214516_t.jpg</node>
  <node id="60452145162" name="BANDARKHAYRANRESERVE_L" label="BANDAR%20KHAYRAN%20RESERVE" type="IMG" description="BANDAR%20KHAYRAN%20RESERVE%20LARGE">Objects/6045214516_n.jpg</node>
  <node id="508339898511" name="DHOFARLAGOONS_T" label="DHOFAR%20LAGOONS" type="IMG" description="DHOFAR%20LAGOONS%20THUMB">Objects/50833989851_t.jpg</node>
  <node id="508339898512" name="DHOFARLAGOONS_L" label="DHOFAR%20LAGOONS" type="IMG" description="DHOFAR%20LAGOONS%20LARGE">Objects/50833989851_n.jpg</node>
  <node id="28310366631" name="KHAWRRURI_T" label="KHAWR%20RURI" type="IMG" description="KHAWR%20RURI%20THUMB">Objects/2831036663_t.jpg</node>
  <node id="28310366632" name="KHAWRRURI_L" label="KHAWR%20RURI" type="IMG" description="KHAWR%20RURI%20LARGE">Objects/2831036663_n.jpg</node>
  <node id="162166334421" name="KHAWRSAWLI_T" label="KHAWR%20SAWLI" type="IMG" description="KHAWR%20SAWLI%20THUMB">Objects/16216633442_t.jpg</node>
  <node id="162166334422" name="KHAWRSAWLI_L" label="KHAWR%20SAWLI" type="IMG" description="KHAWR%20SAWLI%20LARGE">Objects/16216633442_n.jpg</node>
  <node id="105672540251" name="KHAWRALMAGHSAYL_T" label="KHAWR%20AL%20MAGHSAYL" type="IMG" description="KHAWR%20AL%20MAGHSAYL%20THUMB">Objects/10567254025_t.jpg</node>
  <node id="105672540252" name="KHAWRALMAGHSAYL_L" label="KHAWR%20AL%20MAGHSAYL" type="IMG" description="KHAWR%20AL%20MAGHSAYL%20LARGE">Objects/10567254025_n.jpg</node>
  <node id="51228869821" name="KHAWRALQURMALSAGHEERANDALQURMALKABEER_T" label="KHAWRALQURMALSAGHEERANDALQURMALKABEER" type="IMG" description="KHAWRALQURMALSAGHEERANDALQURMALKABEER%20THUMB">Objects/5122886982_t.jpg</node>
  <node id="51228869822" name="KHAWRALQURMALSAGHEERANDALQURMALKABEER_L" label="KHAWRALQURMALSAGHEERANDALQURMALKABEER" type="IMG" description="KHAWRALQURMALSAGHEERANDALQURMALKABEER%20LARGE">Objects/5122886982_n.jpg</node>
  <node id="48218731001" name="KHAWRAWQAD_T" label="KHAWR%20AWQAD" type="IMG" description="KHAWR%20AWQAD%20THUMB">Objects/4821873100_t.jpg</node>
  <node id="48218731002" name="KHAWRAWQAD_L" label="KHAWR%20AWQAD" type="IMG" description="KHAWR%20AWQAD%20LARGE">Objects/4821873100_n.jpg</node>
  <node id="38261484801" name="ADDAHAREEZ_T" label="KHAWR%20AD%20DAHAREEZ" type="IMG" description="KHAWR%20AD%20DAHAREEZ%20THUMB">Objects/3826148480_t.jpg</node>
  <node id="38261484802" name="ADDAHAREEZ_L" label="KHAWR%20AD%20DAHAREEZ" type="IMG" description="KHAWR%20AD%20DAHAREEZ%20LARGE">Objects/3826148480_n.jpg</node>
  <node id="57463644571" name="KHAWRTAQAH_T" label="KHAWR%20TAQAH" type="IMG" description="KHAWR%20TAQAH%20THUMB">Objects/5746364457_t.jpg</node>
  <node id="57463644572" name="KHAWRTAQAH_L" label="KHAWR%20TAQAH" type="IMG" description="KHAWR%20TAQAH%20LARGE">Objects/5746364457_n.jpg</node>
  <node id="69200376491" name="KHAWRNAJD_T" label="KHAWR%20NAJD" type="IMG" description="KHAWR%20NAJD%20THUMB">Objects/6920037649_t.jpg</node>
  <node id="69200376492" name="KHAWRNAJD_L" label="KHAWR%20NAJD" type="IMG" description="KHAWR%20NAJD%20LARGE">Objects/6920037649_n.jpg</node>
  <node id="220887966701" name="KHAWRSHAM_T" label="KHAWR%20SHAM" type="IMG" description="KHAWR%20SHAM%20THUMB">Objects/22088796670_t.jpg</node>
  <node id="220887966702" name="KHAWRSHAM_L" label="KHAWR%20SHAM" type="IMG" description="KHAWR%20SHAM%20LARGE">Objects/22088796670_n.jpg</node>
  <node id="87113829221" name="KHAWRNAJD_T" label="KHAWR%20NAJD" type="IMG" description="KHAWR%20NAJD%20THUMB">Objects/8711382922_t.jpg</node>
  <node id="87113829222" name="KHAWRNAJD_L" label="KHAWR%20NAJD" type="IMG" description="KHAWR%20NAJD%20LARGE">Objects/8711382922_n.jpg</node>
  <node id="151048641661" name="KHAWRALBATAH_T" label="KHAWR%20ALBATAH" type="IMG" description="KHAWR%20ALBATAH%20THUMB">Objects/15104864166_t.jpg</node>
  <node id="151048641662" name="KHAWRALBATAH_L" label="KHAWR%20ALBATAH" type="IMG" description="KHAWR%20ALBATAH%20LARGE">Objects/15104864166_n.jpg</node>
  <node id="68905850291" name="THESTRAITOFHORMUZ_T" label="THE%20STRAIT%20OF%20HORMUZ" type="IMG" description="THE%20STRAIT%20OF%20HORMUZ%20THUMB">Objects/6890585029_t.jpg</node>
  <node id="68905850292" name="THESTRAITOFHORMUZ_L" label="THE%20STRAIT%20OF%20HORMUZ" type="IMG" description="THE%20STRAIT%20OF%20HORMUZ%20LARGE">Objects/6890585029_n.jpg</node>
  <node id="96117777551" name="ROCKGARDEN_T" label="ROCK%20GARDEN" type="IMG" description="ROCK%20GARDEN%20THUMB">Objects/9611777755_t.jpg</node>
  <node id="96117777552" name="ROCKGARDEN_L" label="ROCK%20GARDEN" type="IMG" description="ROCK%20GARDEN%20LARGE">Objects/9611777755_n.jpg</node>
  <node id="83600921031" name="THEEMPTYQUARTER_T" label="THE%20EMPTY%20QUARTER" type="IMG" description="THE%20EMPTY%20QUARTER%20THUMB">Objects/8360092103_t.jpg</node>
  <node id="83600921032" name="THEEMPTYQUARTER_L" label="THE%20EMPTY%20QUARTER" type="IMG" description="THE%20EMPTY%20QUARTER%20LARGE">Objects/8360092103_n.jpg</node>
  <node id="130395077031" name="RAMLATTAWQ_T" label="RAMLAT%20TAWQ" type="IMG" description="RAMLAT%20TAWQ%20THUMB">Objects/13039507703_t.jpg</node>
  <node id="130395077032" name="RAMLATTAWQ_L" label="RAMLAT%20TAWQ" type="IMG" description="RAMLAT%20TAWQ%20LARGE">Objects/13039507703_n.jpg</node>
  <node id="54994833861" name="ASHSHARQIYAHSANDS_T" label="ASHSHARQIYAH%20SANDS" type="IMG" description="ASHSHARQIYAH%20SANDS%20THUMB">Objects/5499483386_t.jpg</node>
  <node id="54994833862" name="ASHSHARQIYAHSANDS_L" label="ASHSHARQIYAH%20SANDS" type="IMG" description="ASHSHARQIYAH%20SANDS%20LARGE">Objects/5499483386_n.jpg</node>
  <node id="174982110661" name="ARZATSPRING_T" label="ARZAT%20SPRING" type="IMG" description="ARZAT%20SPRING%20THUMB">Objects/17498211066_t.jpg</node>
  <node id="174982110662" name="ARZATSPRING_L" label="ARZAT%20SPRING" type="IMG" description="ARZAT%20SPRING%20LARGE">Objects/17498211066_n.jpg</node>
</node>